modulitiz_nano/ModuleEnum.py
modulitiz_nano/ModuloBase64.py
modulitiz_nano/ModuloColorText.py
modulitiz_nano/ModuloDate.py
modulitiz_nano/ModuloFunzioni.py
modulitiz_nano/ModuloListe.py
modulitiz_nano/ModuloNumeri.py
modulitiz_nano/ModuloPyinstaller.py
modulitiz_nano/ModuloStatistiche.py
modulitiz_nano/ModuloStringhe.py
modulitiz_nano/android/ModuloAndroid.py
modulitiz_nano/android/ModuloAndroidAdb.py
modulitiz_nano/android/ModuloAndroidSim.py
modulitiz_nano/android/beans/SmsBean.py
modulitiz_nano/android/enums/AndroidSmsTypeEnum.py
modulitiz_nano/exceptions/ExceptionBase.py
modulitiz_nano/exceptions/ExceptionNoData.py
modulitiz_nano/exceptions/ExceptionOsNotSupported.py
modulitiz_nano/exceptions/ExceptionRuntime.py
modulitiz_nano/files/ModuloFiles.py
modulitiz_nano/files/ModuloLogging.py
modulitiz_nano/files/ModuloZip.py
modulitiz_nano/files/cache/CacheBean.py
modulitiz_nano/files/cache/CacheRam.py
modulitiz_nano/init/AbstractBasicInit.py
modulitiz_nano/init/AbstractInit.py
modulitiz_nano/multithread/ModuloThread.py
modulitiz_nano/multithread/ModuloThreadLogger.py
modulitiz_nano/multithread/ModuloThreadWithCallbackError.py
modulitiz_nano/sistema/EnvVarsEnum.py
modulitiz_nano/sistema/ModuloSystem.py
modulitiz_nano/util/ModuleLint.py
modulitiz_nano/util/beans/conf/AbstractBasicConfBean.py
modulitiz_nano/util/beans/conf/AbstractConfBean.py
modulitiz_nano/util/beans/fileconf/AbstractBasicFileConfBean.py
modulitiz_nano/util/beans/fileconf/AbstractFileConfBean.py
modulitiz_nano/util/beans/globalvar/AbstractGlobalVarBean.py
modulitiz_nano/util/decorators/noAwait.py
modulitiz_nano/util/decorators/timer.py
modulitiz_nano/util/pip/AbstractModuloPip.py
modulitiz_nano/util/pip/ModuloPip.py
modulitiz_nano/util/spooler/AbstractSpooler.py
modulitiz_nano/util/spooler/Spooler.py
modulitiz_nano/util/spooler/beans/QueueBean.py
modulitiz_nano/util/spooler/decorators/spooler.py
modulitiz_nano/util/spooler/exceptions/ExceptionSpooler.py
modulitiz_nano-0.8.0.dist-info/licenses/LICENSE
modulitiz_nano-0.8.0.dist-info/METADATA
modulitiz_nano-0.8.0.dist-info/WHEEL
modulitiz_nano-0.8.0.dist-info/top_level.txt
modulitiz_nano-0.8.0.dist-info/RECORD
