Metadata-Version: 2.4
Name: modulitiz_nano
Version: 0.8.0
Summary: Raccolta dei miei moduli - versione nano
Author-email: tiz <sderfo1234@altervista.org>
Classifier: Programming Language :: Python :: 3
Classifier: Operating System :: OS Independent
Requires-Python: >=3.11
License-File: LICENSE
Requires-Dist: colorama==0.4.6
Requires-Dist: nest-asyncio==1.6.0
Requires-Dist: psutil==7.1.3
Requires-Dist: suntime==1.3.2
Requires-Dist: webcolors==25.10.0
Requires-Dist: vulture==2.14
Dynamic: license-file
